jupyterlab_expand_selection/__init__.py
jupyterlab_expand_selection/_version.py
jupyterlab_expand_selection/labextension/package.json
jupyterlab_expand_selection/labextension/static/353.1a86c0f5e5a12af11bda.js
jupyterlab_expand_selection/labextension/static/392.f8fe3c82b4c648f85e29.js
jupyterlab_expand_selection/labextension/static/444.b3b8a84048c1a9db1299.js
jupyterlab_expand_selection/labextension/static/63.b3b8a84048c1a9db1299.js
jupyterlab_expand_selection/labextension/static/728.4adfef1d66b836915be3.js
jupyterlab_expand_selection/labextension/static/remoteEntry.2ca1f62a68d91323a4d0.js
jupyterlab_expand_selection/labextension/static/style.js
jupyterlab_expand_selection/labextension/static/third-party-licenses.json
jupyterlab_expand_selection-0.4.1.data/data/share/jupyter/labextensions/jupyterlab-expand-selection/package.json
jupyterlab_expand_selection-0.4.1.data/data/share/jupyter/labextensions/jupyterlab-expand-selection/static/353.1a86c0f5e5a12af11bda.js
jupyterlab_expand_selection-0.4.1.data/data/share/jupyter/labextensions/jupyterlab-expand-selection/static/392.f8fe3c82b4c648f85e29.js
jupyterlab_expand_selection-0.4.1.data/data/share/jupyter/labextensions/jupyterlab-expand-selection/static/444.b3b8a84048c1a9db1299.js
jupyterlab_expand_selection-0.4.1.data/data/share/jupyter/labextensions/jupyterlab-expand-selection/static/63.b3b8a84048c1a9db1299.js
jupyterlab_expand_selection-0.4.1.data/data/share/jupyter/labextensions/jupyterlab-expand-selection/static/728.4adfef1d66b836915be3.js
jupyterlab_expand_selection-0.4.1.data/data/share/jupyter/labextensions/jupyterlab-expand-selection/static/remoteEntry.2ca1f62a68d91323a4d0.js
jupyterlab_expand_selection-0.4.1.data/data/share/jupyter/labextensions/jupyterlab-expand-selection/static/style.js
jupyterlab_expand_selection-0.4.1.data/data/share/jupyter/labextensions/jupyterlab-expand-selection/static/third-party-licenses.json
jupyterlab_expand_selection-0.4.1.dist-info/METADATA
jupyterlab_expand_selection-0.4.1.dist-info/WHEEL
jupyterlab_expand_selection-0.4.1.dist-info/licenses/LICENSE
jupyterlab_expand_selection-0.4.1.dist-info/RECORD
