Metadata-Version: 2.4
Name: jupyterlab-expand-selection
Version: 0.4.1
Summary: A JupyterLab extension that introduces expand/shrink selection commands
Project-URL: Homepage, https://github.com/i-aki-y/jupyterlab-expand-selection
Project-URL: Bug Tracker, https://github.com/i-aki-y/jupyterlab-expand-selection/issues
Project-URL: Repository, https://github.com/i-aki-y/jupyterlab-expand-selection.git
Author-email: Akiyuki Ishikawa <aki.y.ishikawa@gmail.com>
License: BSD 3-Clause License
License-File: LICENSE
Keywords: jupyter,jupyterlab,jupyterlab-extension
Classifier: Framework :: Jupyter
Classifier: Framework :: Jupyter :: JupyterLab
Classifier: Framework :: Jupyter :: JupyterLab :: 4
Classifier: Framework :: Jupyter :: JupyterLab :: Extensions
Classifier: Framework :: Jupyter :: JupyterLab :: Extensions :: Prebuilt
Classifier: License :: OSI Approved :: BSD License
Classifier: Programming Language :: Python
Classifier: Programming Language :: Python :: 3
Classifier: Programming Language :: Python :: 3.9
Classifier: Programming Language :: Python :: 3.10
Classifier: Programming Language :: Python :: 3.11
Classifier: Programming Language :: Python :: 3.12
Classifier: Programming Language :: Python :: 3.13
Requires-Python: >=3.9
